{
  "url": "/api/mst/getPvePlayRewardMstList",
  "status": 200,
  "payload": {
    "mstList": [
      {
        "pvePlayRewardMstId": 10111,
        "pveMapMstId": 101,
        "grade": 1,
        "groupId": 10111
      },
      {
        "pvePlayRewardMstId": 10112,
        "pveMapMstId": 101,
        "grade": 2,
        "groupId": 10112
      },
      {
        "pvePlayRewardMstId": 10113,
        "pveMapMstId": 101,
        "grade": 3,
        "groupId": 10113
      },
      {
        "pvePlayRewardMstId": 10114,
        "pveMapMstId": 101,
        "grade": 4,
        "groupId": 10114
      },
      {
        "pvePlayRewardMstId": 10115,
        "pveMapMstId": 101,
        "grade": 5,
        "groupId": 10115
      },
      {
        "pvePlayRewardMstId": 10211,
        "pveMapMstId": 102,
        "grade": 1,
        "groupId": 10211
      },
      {
        "pvePlayRewardMstId": 10212,
        "pveMapMstId": 102,
        "grade": 2,
        "groupId": 10212
      },
      {
        "pvePlayRewardMstId": 10213,
        "pveMapMstId": 102,
        "grade": 3,
        "groupId": 10213
      },
      {
        "pvePlayRewardMstId": 10214,
        "pveMapMstId": 102,
        "grade": 4,
        "groupId": 10214
      },
      {
        "pvePlayRewardMstId": 10215,
        "pveMapMstId": 102,
        "grade": 5,
        "groupId": 10215
      },
      {
        "pvePlayRewardMstId": 10311,
        "pveMapMstId": 103,
        "grade": 1,
        "groupId": 10311
      },
      {
        "pvePlayRewardMstId": 10312,
        "pveMapMstId": 103,
        "grade": 2,
        "groupId": 10312
      },
      {
        "pvePlayRewardMstId": 10313,
        "pveMapMstId": 103,
        "grade": 3,
        "groupId": 10313
      },
      {
        "pvePlayRewardMstId": 10314,
        "pveMapMstId": 103,
        "grade": 4,
        "groupId": 10314
      },
      {
        "pvePlayRewardMstId": 10315,
        "pveMapMstId": 103,
        "grade": 5,
        "groupId": 10315
      },
      {
        "pvePlayRewardMstId": 10411,
        "pveMapMstId": 104,
        "grade": 1,
        "groupId": 10411
      },
      {
        "pvePlayRewardMstId": 10412,
        "pveMapMstId": 104,
        "grade": 2,
        "groupId": 10412
      },
      {
        "pvePlayRewardMstId": 10413,
        "pveMapMstId": 104,
        "grade": 3,
        "groupId": 10413
      },
      {
        "pvePlayRewardMstId": 10414,
        "pveMapMstId": 104,
        "grade": 4,
        "groupId": 10414
      },
      {
        "pvePlayRewardMstId": 10415,
        "pveMapMstId": 104,
        "grade": 5,
        "groupId": 10415
      },
      {
        "pvePlayRewardMstId": 10511,
        "pveMapMstId": 105,
        "grade": 1,
        "groupId": 10511
      },
      {
        "pvePlayRewardMstId": 10512,
        "pveMapMstId": 105,
        "grade": 2,
        "groupId": 10512
      },
      {
        "pvePlayRewardMstId": 10513,
        "pveMapMstId": 105,
        "grade": 3,
        "groupId": 10513
      },
      {
        "pvePlayRewardMstId": 10514,
        "pveMapMstId": 105,
        "grade": 4,
        "groupId": 10514
      },
      {
        "pvePlayRewardMstId": 10515,
        "pveMapMstId": 105,
        "grade": 5,
        "groupId": 10515
      },
      {
        "pvePlayRewardMstId": 10611,
        "pveMapMstId": 106,
        "grade": 1,
        "groupId": 10611
      },
      {
        "pvePlayRewardMstId": 10612,
        "pveMapMstId": 106,
        "grade": 2,
        "groupId": 10612
      },
      {
        "pvePlayRewardMstId": 10613,
        "pveMapMstId": 106,
        "grade": 3,
        "groupId": 10613
      },
      {
        "pvePlayRewardMstId": 10614,
        "pveMapMstId": 106,
        "grade": 4,
        "groupId": 10614
      },
      {
        "pvePlayRewardMstId": 10615,
        "pveMapMstId": 106,
        "grade": 5,
        "groupId": 10615
      },
      {
        "pvePlayRewardMstId": 10711,
        "pveMapMstId": 107,
        "grade": 1,
        "groupId": 10711
      },
      {
        "pvePlayRewardMstId": 10712,
        "pveMapMstId": 107,
        "grade": 2,
        "groupId": 10712
      },
      {
        "pvePlayRewardMstId": 10713,
        "pveMapMstId": 107,
        "grade": 3,
        "groupId": 10713
      },
      {
        "pvePlayRewardMstId": 10714,
        "pveMapMstId": 107,
        "grade": 4,
        "groupId": 10714
      },
      {
        "pvePlayRewardMstId": 10715,
        "pveMapMstId": 107,
        "grade": 5,
        "groupId": 10715
      },
      {
        "pvePlayRewardMstId": 10811,
        "pveMapMstId": 108,
        "grade": 1,
        "groupId": 10811
      },
      {
        "pvePlayRewardMstId": 10812,
        "pveMapMstId": 108,
        "grade": 2,
        "groupId": 10812
      },
      {
        "pvePlayRewardMstId": 10813,
        "pveMapMstId": 108,
        "grade": 3,
        "groupId": 10813
      },
      {
        "pvePlayRewardMstId": 10814,
        "pveMapMstId": 108,
        "grade": 4,
        "groupId": 10814
      },
      {
        "pvePlayRewardMstId": 10815,
        "pveMapMstId": 108,
        "grade": 5,
        "groupId": 10815
      },
      {
        "pvePlayRewardMstId": 10911,
        "pveMapMstId": 109,
        "grade": 1,
        "groupId": 10911
      },
      {
        "pvePlayRewardMstId": 10912,
        "pveMapMstId": 109,
        "grade": 2,
        "groupId": 10912
      },
      {
        "pvePlayRewardMstId": 10913,
        "pveMapMstId": 109,
        "grade": 3,
        "groupId": 10913
      },
      {
        "pvePlayRewardMstId": 10914,
        "pveMapMstId": 109,
        "grade": 4,
        "groupId": 10914
      },
      {
        "pvePlayRewardMstId": 10915,
        "pveMapMstId": 109,
        "grade": 5,
        "groupId": 10915
      },
      {
        "pvePlayRewardMstId": 11011,
        "pveMapMstId": 110,
        "grade": 1,
        "groupId": 11011
      },
      {
        "pvePlayRewardMstId": 11012,
        "pveMapMstId": 110,
        "grade": 2,
        "groupId": 11012
      },
      {
        "pvePlayRewardMstId": 11013,
        "pveMapMstId": 110,
        "grade": 3,
        "groupId": 11013
      },
      {
        "pvePlayRewardMstId": 11014,
        "pveMapMstId": 110,
        "grade": 4,
        "groupId": 11014
      },
      {
        "pvePlayRewardMstId": 11015,
        "pveMapMstId": 110,
        "grade": 5,
        "groupId": 11015
      },
      {
        "pvePlayRewardMstId": 11111,
        "pveMapMstId": 111,
        "grade": 1,
        "groupId": 11111
      },
      {
        "pvePlayRewardMstId": 11112,
        "pveMapMstId": 111,
        "grade": 2,
        "groupId": 11112
      },
      {
        "pvePlayRewardMstId": 11113,
        "pveMapMstId": 111,
        "grade": 3,
        "groupId": 11113
      },
      {
        "pvePlayRewardMstId": 11114,
        "pveMapMstId": 111,
        "grade": 4,
        "groupId": 11114
      },
      {
        "pvePlayRewardMstId": 11115,
        "pveMapMstId": 111,
        "grade": 5,
        "groupId": 11115
      },
      {
        "pvePlayRewardMstId": 11211,
        "pveMapMstId": 112,
        "grade": 1,
        "groupId": 11211
      },
      {
        "pvePlayRewardMstId": 11212,
        "pveMapMstId": 112,
        "grade": 2,
        "groupId": 11212
      },
      {
        "pvePlayRewardMstId": 11213,
        "pveMapMstId": 112,
        "grade": 3,
        "groupId": 11213
      },
      {
        "pvePlayRewardMstId": 11214,
        "pveMapMstId": 112,
        "grade": 4,
        "groupId": 11214
      },
      {
        "pvePlayRewardMstId": 11215,
        "pveMapMstId": 112,
        "grade": 5,
        "groupId": 11215
      },
      {
        "pvePlayRewardMstId": 11311,
        "pveMapMstId": 113,
        "grade": 1,
        "groupId": 11311
      },
      {
        "pvePlayRewardMstId": 11312,
        "pveMapMstId": 113,
        "grade": 2,
        "groupId": 11312
      },
      {
        "pvePlayRewardMstId": 11313,
        "pveMapMstId": 113,
        "grade": 3,
        "groupId": 11313
      },
      {
        "pvePlayRewardMstId": 11314,
        "pveMapMstId": 113,
        "grade": 4,
        "groupId": 11314
      },
      {
        "pvePlayRewardMstId": 11315,
        "pveMapMstId": 113,
        "grade": 5,
        "groupId": 11315
      },
      {
        "pvePlayRewardMstId": 11411,
        "pveMapMstId": 114,
        "grade": 1,
        "groupId": 11411
      },
      {
        "pvePlayRewardMstId": 11412,
        "pveMapMstId": 114,
        "grade": 2,
        "groupId": 11412
      },
      {
        "pvePlayRewardMstId": 11413,
        "pveMapMstId": 114,
        "grade": 3,
        "groupId": 11413
      },
      {
        "pvePlayRewardMstId": 11414,
        "pveMapMstId": 114,
        "grade": 4,
        "groupId": 11414
      },
      {
        "pvePlayRewardMstId": 11415,
        "pveMapMstId": 114,
        "grade": 5,
        "groupId": 11415
      },
      {
        "pvePlayRewardMstId": 11511,
        "pveMapMstId": 115,
        "grade": 1,
        "groupId": 11511
      },
      {
        "pvePlayRewardMstId": 11512,
        "pveMapMstId": 115,
        "grade": 2,
        "groupId": 11512
      },
      {
        "pvePlayRewardMstId": 11513,
        "pveMapMstId": 115,
        "grade": 3,
        "groupId": 11513
      },
      {
        "pvePlayRewardMstId": 11514,
        "pveMapMstId": 115,
        "grade": 4,
        "groupId": 11514
      },
      {
        "pvePlayRewardMstId": 11515,
        "pveMapMstId": 115,
        "grade": 5,
        "groupId": 11515
      },
      {
        "pvePlayRewardMstId": 11611,
        "pveMapMstId": 116,
        "grade": 1,
        "groupId": 11611
      },
      {
        "pvePlayRewardMstId": 11612,
        "pveMapMstId": 116,
        "grade": 2,
        "groupId": 11612
      },
      {
        "pvePlayRewardMstId": 11613,
        "pveMapMstId": 116,
        "grade": 3,
        "groupId": 11613
      },
      {
        "pvePlayRewardMstId": 11614,
        "pveMapMstId": 116,
        "grade": 4,
        "groupId": 11614
      },
      {
        "pvePlayRewardMstId": 11615,
        "pveMapMstId": 116,
        "grade": 5,
        "groupId": 11615
      },
      {
        "pvePlayRewardMstId": 11711,
        "pveMapMstId": 117,
        "grade": 1,
        "groupId": 11711
      },
      {
        "pvePlayRewardMstId": 11712,
        "pveMapMstId": 117,
        "grade": 2,
        "groupId": 11712
      },
      {
        "pvePlayRewardMstId": 11713,
        "pveMapMstId": 117,
        "grade": 3,
        "groupId": 11713
      },
      {
        "pvePlayRewardMstId": 11714,
        "pveMapMstId": 117,
        "grade": 4,
        "groupId": 11714
      },
      {
        "pvePlayRewardMstId": 11715,
        "pveMapMstId": 117,
        "grade": 5,
        "groupId": 11715
      },
      {
        "pvePlayRewardMstId": 11811,
        "pveMapMstId": 118,
        "grade": 1,
        "groupId": 11811
      },
      {
        "pvePlayRewardMstId": 11812,
        "pveMapMstId": 118,
        "grade": 2,
        "groupId": 11812
      },
      {
        "pvePlayRewardMstId": 11813,
        "pveMapMstId": 118,
        "grade": 3,
        "groupId": 11813
      },
      {
        "pvePlayRewardMstId": 11814,
        "pveMapMstId": 118,
        "grade": 4,
        "groupId": 11814
      },
      {
        "pvePlayRewardMstId": 11815,
        "pveMapMstId": 118,
        "grade": 5,
        "groupId": 11815
      },
      {
        "pvePlayRewardMstId": 11911,
        "pveMapMstId": 119,
        "grade": 1,
        "groupId": 11911
      },
      {
        "pvePlayRewardMstId": 11912,
        "pveMapMstId": 119,
        "grade": 2,
        "groupId": 11912
      },
      {
        "pvePlayRewardMstId": 11913,
        "pveMapMstId": 119,
        "grade": 3,
        "groupId": 11913
      },
      {
        "pvePlayRewardMstId": 11914,
        "pveMapMstId": 119,
        "grade": 4,
        "groupId": 11914
      },
      {
        "pvePlayRewardMstId": 11915,
        "pveMapMstId": 119,
        "grade": 5,
        "groupId": 11915
      },
      {
        "pvePlayRewardMstId": 12011,
        "pveMapMstId": 120,
        "grade": 1,
        "groupId": 12011
      },
      {
        "pvePlayRewardMstId": 12012,
        "pveMapMstId": 120,
        "grade": 2,
        "groupId": 12012
      },
      {
        "pvePlayRewardMstId": 12013,
        "pveMapMstId": 120,
        "grade": 3,
        "groupId": 12013
      },
      {
        "pvePlayRewardMstId": 12014,
        "pveMapMstId": 120,
        "grade": 4,
        "groupId": 12014
      },
      {
        "pvePlayRewardMstId": 12015,
        "pveMapMstId": 120,
        "grade": 5,
        "groupId": 12015
      },
      {
        "pvePlayRewardMstId": 12111,
        "pveMapMstId": 121,
        "grade": 1,
        "groupId": 12111
      },
      {
        "pvePlayRewardMstId": 12112,
        "pveMapMstId": 121,
        "grade": 2,
        "groupId": 12112
      },
      {
        "pvePlayRewardMstId": 12113,
        "pveMapMstId": 121,
        "grade": 3,
        "groupId": 12113
      },
      {
        "pvePlayRewardMstId": 12114,
        "pveMapMstId": 121,
        "grade": 4,
        "groupId": 12114
      },
      {
        "pvePlayRewardMstId": 12115,
        "pveMapMstId": 121,
        "grade": 5,
        "groupId": 12115
      }
    ]
  }
}