{
  "url": "/api/mst/getGigantHugeMissionMstModelList",
  "status": 200,
  "payload": {
    "mstList": [
      {
        "gigantHugeMissionMstId": 1,
        "name": "レアスキルを1回使う",
        "conditionType": 1,
        "conditionId": 0,
        "conditionValue": 1
      },
      {
        "gigantHugeMissionMstId": 2,
        "name": "オーダーを1回使ってクリア",
        "conditionType": 2,
        "conditionId": 0,
        "conditionValue": 1
      },
      {
        "gigantHugeMissionMstId": 3,
        "name": "メモリアスキルを1回以上使ってクリア",
        "conditionType": 3,
        "conditionId": 0,
        "conditionValue": 1
      },
      {
        "gigantHugeMissionMstId": 2001,
        "name": "レアスキルを1回使う",
        "conditionType": 1,
        "conditionId": 0,
        "conditionValue": 1
      },
      {
        "gigantHugeMissionMstId": 2002,
        "name": "オーダーを1回使ってクリア",
        "conditionType": 2,
        "conditionId": 0,
        "conditionValue": 1
      },
      {
        "gigantHugeMissionMstId": 2003,
        "name": "メモリアスキルを1回以上使ってクリア",
        "conditionType": 3,
        "conditionId": 0,
        "conditionValue": 1
      }
    ]
  }
}